infi.recipe.js_requirements-0.2.2-py2.7-nspkg.pth
infi/recipe/js_requirements/__init__.py
infi.recipe.js_requirements-0.2.2.dist-info/METADATA
infi.recipe.js_requirements-0.2.2.dist-info/RECORD
infi.recipe.js_requirements-0.2.2.dist-info/WHEEL
infi.recipe.js_requirements-0.2.2.dist-info/entry_points.txt
infi.recipe.js_requirements-0.2.2.dist-info/namespace_packages.txt
infi.recipe.js_requirements-0.2.2.dist-info/top_level.txt
