Metadata-Version: 2.1
Name: infi.recipe.js-requirements
Version: 0.2.2
Summary: buildout recipe for downloading, extracting and dependency parsing for JavaScript
Home-page: https://github.com/Infinidat/infi.recipe.js_requirements
Author: fanchi
Author-email: rbelio@infinidat.com
License: BSD
Platform: UNKNOWN
Classifier: Intended Audience :: Developers
Classifier: Intended Audience :: System Administrators
Classifier: License :: OSI Approved :: BSD License
Classifier: Operating System :: OS Independent
Classifier: Programming Language :: Python
Classifier: Programming Language :: Python :: 2
Classifier: Programming Language :: Python :: 3
Classifier: Topic :: Software Development :: Libraries :: Python Modules
Requires-Dist: setuptools (>=32.0)
Requires-Dist: zc.buildout
Requires-Dist: semantic-version
Requires-Dist: six
Requires-Dist: requests
